<History Size="8">
	<save_point_1 UserName="ivan" UserId="-1" Time="2023.07.29 21_33_15"/>
	<save_point_2 UserName="ivan" UserId="-1" Time="2023.07.29 21_33_15"/>
	<save_point_3 UserName="ivan" UserId="-1" Time="2023.07.29 21_33_28"/>
	<save_point_4 UserName="ivan" UserId="-1" Time="2023.07.29 21_36_37"/>
	<save_point_5 UserName="ivan" UserId="-1" Time="2023.07.29 21_40_46"/>
	<save_point_6 UserName="ivan" UserId="-1" Time="2023.07.29 21_48_53"/>
	<save_point_7 UserName="ivan" UserId="-1" Time="2023.07.29 21_49_00"/>
	<save_point_8 UserName="ivan" UserId="-1" Time="2023.07.29 22_01_34"/>
</History>
